pyside6_test_uv/__init__.py
pyside6_test_uv/__main__.py
pyside6_test_uv/app.py
pyside6_test_uv/main_window.py
pyside6_test_uv/main_window.ui
pyside6_test_uv/main_window_ui.py
pyside6_test_uv/version.py
pyside6_test_uv-0.1.5.dist-info/METADATA
pyside6_test_uv-0.1.5.dist-info/WHEEL
pyside6_test_uv-0.1.5.dist-info/entry_points.txt
pyside6_test_uv-0.1.5.dist-info/top_level.txt
pyside6_test_uv-0.1.5.dist-info/RECORD
